thonny_calliope-0.2b1.dist-info/METADATA
thonny_calliope-0.2b1.dist-info/RECORD
thonny_calliope-0.2b1.dist-info/WHEEL
thonny_calliope-0.2b1.dist-info/top_level.txt
thonnycontrib/calliope/__init__.py
thonnycontrib/calliope/api_stubs/antigravity.py
thonnycontrib/calliope/api_stubs/array.py
thonnycontrib/calliope/api_stubs/audio.py
thonnycontrib/calliope/api_stubs/builtins.py
thonnycontrib/calliope/api_stubs/collections.py
thonnycontrib/calliope/api_stubs/gc.py
thonnycontrib/calliope/api_stubs/love.py
thonnycontrib/calliope/api_stubs/machine.py
thonnycontrib/calliope/api_stubs/math.py
thonnycontrib/calliope/api_stubs/microbit.py
thonnycontrib/calliope/api_stubs/micropython.py
thonnycontrib/calliope/api_stubs/music.py
thonnycontrib/calliope/api_stubs/neopixel.py
thonnycontrib/calliope/api_stubs/os.py
thonnycontrib/calliope/api_stubs/radio.py
thonnycontrib/calliope/api_stubs/random.py
thonnycontrib/calliope/api_stubs/speech.py
thonnycontrib/calliope/api_stubs/struct.py
thonnycontrib/calliope/api_stubs/sys.py
thonnycontrib/calliope/api_stubs/this.py
thonnycontrib/calliope/api_stubs/time.py
thonnycontrib/calliope/api_stubs/ucollections.py
thonnycontrib/calliope/api_stubs/ustruct.py
thonnycontrib/calliope/api_stubs/utime.py
thonnycontrib/calliope/firmware/MicroPython_1.9.2-34.hex
